{"/about/":"https://irchamali.github.io/","/about.html":"https://irchamali.github.io/","/resume-json":"https://irchamali.github.io/cv-json/","/resume":"https://irchamali.github.io/cv/","/md/":"https://irchamali.github.io/markdown/","/markdown.html":"https://irchamali.github.io/markdown/","/nmp/":"https://irchamali.github.io/non-menu-page/","/nmp.html":"https://irchamali.github.io/non-menu-page/","/posts/":"https://irchamali.github.io/year-archive/","/blog/":"https://irchamali.github.io/year-archive/"}